LICENSE
README.md
setup.cfg
setup.py
databay/__init__.py
databay/base_planner.py
databay/config.py
databay/errors.py
databay/inlet.py
databay/link.py
databay/outlet.py
databay/record.py
databay.egg-info/PKG-INFO
databay.egg-info/SOURCES.txt
databay.egg-info/dependency_links.txt
databay.egg-info/requires.txt
databay.egg-info/top_level.txt
databay/inlets/__init__.py
databay/inlets/file_inlet.py
databay/inlets/http_inlet.py
databay/inlets/null_inlet.py
databay/inlets/random_int_inlet.py
databay/misc/__init__.py
databay/misc/inlet_tester.py
databay/misc/logs.py
databay/outlets/__init__.py
databay/outlets/csv_outlet.py
databay/outlets/file_outlet.py
databay/outlets/mongo_outlet.py
databay/outlets/null_outlet.py
databay/outlets/print_outlet.py
databay/planners/__init__.py
databay/planners/aps_planner.py
databay/planners/schedule_planner.py
databay/support/__init__.py
databay/support/buffers.py
test/test_utils.py