Metadata-Version: 2.1
Name: databay
Version: 0.3.0
Summary: Databay is a Python interface for scheduled data transfer. It facilitates transfer of (any) data from A to B, on a scheduled interval.
Home-page: https://github.com/Voyz/databay
Author: Voy Zan, Charles Pierse
Author-email: voy1982@yahoo.co.uk
License: Apache-2.0
Keywords: data transfer,data production,data consumption,schedule,scheduled data transfer,scheduled transfer,data flow,repeated data transfer
Platform: UNKNOWN
Classifier: Development Status :: 4 - Beta
Classifier: Intended Audience :: Developers
Classifier: Topic :: Software Development :: Libraries :: Python Modules
Classifier: Programming Language :: Python :: 3.6
Classifier: Programming Language :: Python :: 3.7
Classifier: Programming Language :: Python :: 3.8
Classifier: Programming Language :: Python :: 3.9
Provides-Extra: HttpInlet
Provides-Extra: MongoOutlet
Provides-Extra: all
License-File: LICENSE
